{"is_source_file": true, "format": "JavaScript (React component)", "description": "React component for an accessible modal dialog displaying recipe details with focus trap and keyboard handling.", "external_files": ["react"], "external_methods": ["React.useEffect", "React.useMemo", "React.useRef"], "published": ["RecipeDetailsModal"], "classes": [], "methods": [{"name": "getFocusableElements(container)", "description": "Utility function that retrieves all focusable elements within a given container for focus management.", "scope": "", "scopeKind": ""}, {"name": "RecipeDetailsModal({ recipe, isOpen, onClose })", "scope": "", "scopeKind": "", "description": "unavailable"}], "calls": ["document.querySelectorAll", "Array.from", "setTimeout", "document.addEventListener", "document.removeEventListener"], "search-terms": ["RecipeDetailsModal", "accessible modal", "React focus trap", "recipe details", "modal dialog React"], "state": 2, "file_id": 20, "knowledge_revision": 52, "git_revision": "797b75a0b06def72c6c7bd102c598b6e8f2c4c6f", "ctags": [{"_type": "tag", "name": "RecipeDetailsModal", "path": "/home/kavia/workspace/code-generation/recipe-explorer-51407-51416/frontend_react/src/components/RecipeDetailsModal.js", "pattern": "/^export default function RecipeDetailsModal({ recipe, isOpen, onClose }) {$/", "language": "JavaScript", "kind": "function", "signature": "({ recipe, isOpen, onClose })"}, {"_type": "tag", "name": "closeButtonRef", "path": "/home/kavia/workspace/code-generation/recipe-explorer-51407-51416/frontend_react/src/components/RecipeDetailsModal.js", "pattern": "/^            ref={closeButtonRef}$/", "language": "JavaScript", "kind": "field", "scope": "RecipeDetailsModal.ref", "scopeKind": "class"}, {"_type": "tag", "name": "dialogRef", "path": "/home/kavia/workspace/code-generation/recipe-explorer-51407-51416/frontend_react/src/components/RecipeDetailsModal.js", "pattern": "/^        ref={dialogRef}$/", "language": "JavaScript", "kind": "field", "scope": "RecipeDetailsModal.ref", "scopeKind": "class"}, {"_type": "tag", "name": "getFocusableElements", "path": "/home/kavia/workspace/code-generation/recipe-explorer-51407-51416/frontend_react/src/components/RecipeDetailsModal.js", "pattern": "/^function getFocusableElements(container) {$/", "language": "JavaScript", "kind": "function", "signature": "(container)"}, {"_type": "tag", "name": "onClose", "path": "/home/kavia/workspace/code-generation/recipe-explorer-51407-51416/frontend_react/src/components/RecipeDetailsModal.js", "pattern": "/^            onClick={onClose}$/", "language": "JavaScript", "kind": "field", "scope": "RecipeDetailsModal.onClick", "scopeKind": "class"}, {"_type": "tag", "name": "titleId", "path": "/home/kavia/workspace/code-generation/recipe-explorer-51407-51416/frontend_react/src/components/RecipeDetailsModal.js", "pattern": "/^        aria-labelledby={titleId}$/", "language": "JavaScript", "kind": "field", "scope": "RecipeDetailsModal.aria", "scopeKind": "class"}], "hash": "f8bd66d09cdd373068305b44346605ea", "format-version": 4, "code-base-name": "frontend_react", "filename": "frontend_react/src/components/RecipeDetailsModal.js", "fields": [{"name": "ref={closeButtonRef}", "scope": "RecipeDetailsModal.ref", "scopeKind": "class", "description": "unavailable"}, {"name": "ref={dialogRef}", "scope": "RecipeDetailsModal.ref", "scopeKind": "class", "description": "unavailable"}, {"name": "onClick={onClose}", "scope": "RecipeDetailsModal.onClick", "scopeKind": "class", "description": "unavailable"}, {"name": "aria-labelledby={titleId}", "scope": "RecipeDetailsModal.aria", "scopeKind": "class", "description": "unavailable"}], "revision_history": [{"52": "797b75a0b06def72c6c7bd102c598b6e8f2c4c6f"}]}